{
  "resources":[
    {
      "id":441988,
      "name":"TVA",
      "parent":{
        "id":159,
        "resource_uri":"/v2/categories/159",
        "resource_type":"category"
      },
      "resource_uri":"/v2/categories/441988",
      "resource_type":"category"
    },
    {
      "id":441900,
      "name":"Marketing",
      "parent":{
        "id":166,
        "resource_uri":"/v2/categories/166",
        "resource_type":"category"
      },
      "resource_uri":"/v2/categories/441900",
      "resource_type":"category"
    },
    {
      "id":441899,
      "name":"Frais juridique",
      "parent":{
        "id":166,
        "resource_uri":"/v2/categories/166",
        "resource_type":"category"
      },
      "resource_uri":"/v2/categories/441899",
      "resource_type":"category"
    },
    {
      "id":441898,
      "name":"Taxe d'apprentissage",
      "parent":{
        "id":166,
        "resource_uri":"/v2/categories/166",
        "resource_type":"category"
      },
      "resource_uri":"/v2/categories/441898",
      "resource_type":"category"
    },
    {
      "id":441897,
      "name":"Prévoyance",
      "parent":{
        "id":166,
        "resource_uri":"/v2/categories/166",
        "resource_type":"category"
      },
      "resource_uri":"/v2/categories/441897",
      "resource_type":"category"
    },
    {
      "id":441896,
      "name":"Sous-traitance",
      "parent":{
        "id":166,
        "resource_uri":"/v2/categories/166",
        "resource_type":"category"
      },
      "resource_uri":"/v2/categories/441896",
      "resource_type":"category"
    },
    {
      "id":441895,
      "name":"Conseils",
      "parent":{
        "id":166,
        "resource_uri":"/v2/categories/166",
        "resource_type":"category"
      },
      "resource_uri":"/v2/categories/441895",
      "resource_type":"category"
    },
    {
      "id":441894,
      "name":"Emprunt",
      "parent":{
        "id":2,
        "resource_uri":"/v2/categories/2",
        "resource_type":"category"
      },
      "resource_uri":"/v2/categories/441894",
      "resource_type":"category"
    },
    {
      "id":441893,
      "name":"Subventions",
      "parent":{
        "id":2,
        "resource_uri":"/v2/categories/2",
        "resource_type":"category"
      },
      "resource_uri":"/v2/categories/441893",
      "resource_type":"category"
    },
    {
      "id":441892,
      "name":"Frais de recrutement",
      "parent":{
        "id":166,
        "resource_uri":"/v2/categories/166",
        "resource_type":"category"
      },
      "resource_uri":"/v2/categories/441892",
      "resource_type":"category"
    },
    {
      "id":441891,
      "name":"Rémunérations dirigeants",
      "parent":{
        "id":166,
        "resource_uri":"/v2/categories/166",
        "resource_type":"category"
      },
      "resource_uri":"/v2/categories/441891",
      "resource_type":"category"
    },
    {
      "id":441890,
      "name":"Salaires",
      "parent":{
        "id":166,
        "resource_uri":"/v2/categories/166",
        "resource_type":"category"
      },
      "resource_uri":"/v2/categories/441890",
      "resource_type":"category"
    },
    {
      "id":441889,
      "name":"Comptabilité",
      "parent":{
        "id":166,
        "resource_uri":"/v2/categories/166",
        "resource_type":"category"
      },
      "resource_uri":"/v2/categories/441889",
      "resource_type":"category"
    },
    {
      "id":441888,
      "name":"Licenses",
      "parent":{
        "id":162,
        "resource_uri":"/v2/categories/162",
        "resource_type":"category"
      },
      "resource_uri":"/v2/categories/441888",
      "resource_type":"category"
    },
    {
      "id":441886,
      "name":"Cotisations Sociales",
      "parent":{
        "id":166,
        "resource_uri":"/v2/categories/166",
        "resource_type":"category"
      },
      "resource_uri":"/v2/categories/441886",
      "resource_type":"category"
    },
    {
      "id":328,
      "name":"Charges diverses",
      "parent":{
        "id":161,
        "resource_uri":"/v2/categories/161",
        "resource_type":"category"
      },
      "resource_uri":"/v2/categories/328",
      "resource_type":"category"
    },
    {
      "id":327,
      "name":"Allocations et pensions",
      "parent":{
        "id":2,
        "resource_uri":"/v2/categories/2",
        "resource_type":"category"
      },
      "resource_uri":"/v2/categories/327",
      "resource_type":"category"
    },
    {
      "id":326,
      "name":"Virements internes",
      "parent":{
        "id":303,
        "resource_uri":"/v2/categories/303",
        "resource_type":"category"
      },
      "resource_uri":"/v2/categories/326",
      "resource_type":"category"
    },
    {
      "id":325,
      "name":"Dentiste",
      "parent":{
        "id":163,
        "resource_uri":"/v2/categories/163",
        "resource_type":"category"
      },
      "resource_uri":"/v2/categories/325",
      "resource_type":"category"
    },
    {
      "id":324,
      "name":"Pressing",
      "parent":{
        "id":160,
        "resource_uri":"/v2/categories/160",
        "resource_type":"category"
      },
      "resource_uri":"/v2/categories/324",
      "resource_type":"category"
    },
    {
      "id":323,
      "name":"Extérieur et jardin",
      "parent":{
        "id":161,
        "resource_uri":"/v2/categories/161",
        "resource_type":"category"
      },
      "resource_uri":"/v2/categories/323",
      "resource_type":"category"
    },
    {
      "id":322,
      "name":"Opticien / Ophtalmo.",
      "parent":{
        "id":163,
        "resource_uri":"/v2/categories/163",
        "resource_type":"category"
      },
      "resource_uri":"/v2/categories/322",
      "resource_type":"category"
    },
    {
      "id":321,
      "name":"Esthétique",
      "parent":{
        "id":315,
        "resource_uri":"/v2/categories/315",
        "resource_type":"category"
      },
      "resource_uri":"/v2/categories/321",
      "resource_type":"category"
    },
    {
      "id":320,
      "name":"Sortie au restaurant",
      "parent":{
        "id":170,
        "resource_uri":"/v2/categories/170",
        "resource_type":"category"
      },
      "resource_uri":"/v2/categories/320",
      "resource_type":"category"
    },
    {
      "id":319,
      "name":"Films & DVDs",
      "parent":{
        "id":162,
        "resource_uri":"/v2/categories/162",
        "resource_type":"category"
      },
      "resource_uri":"/v2/categories/319",
      "resource_type":"category"
    },
    {
      "id":318,
      "name":"Musique",
      "parent":{
        "id":162,
        "resource_uri":"/v2/categories/162",
        "resource_type":"category"
      },
      "resource_uri":"/v2/categories/318",
      "resource_type":"category"
    },
    {
      "id":317,
      "name":"Esthétique & Soins - Autres",
      "parent":{
        "id":315,
        "resource_uri":"/v2/categories/315",
        "resource_type":"category"
      },
      "resource_uri":"/v2/categories/317",
      "resource_type":"category"
    },
    {
      "id":316,
      "name":"Spa & Massage",
      "parent":{
        "id":315,
        "resource_uri":"/v2/categories/315",
        "resource_type":"category"
      },
      "resource_uri":"/v2/categories/316",
      "resource_type":"category"
    },
    {
      "id":315,
      "name":"Esthétique & Soins",
      "parent":null,
      "resource_uri":"/v2/categories/315",
      "resource_type":"category"
    },
    {
      "id":314,
      "name":"Loyers reçus",
      "parent":{
        "id":2,
        "resource_uri":"/v2/categories/2",
        "resource_type":"category"
      },
      "resource_uri":"/v2/categories/314",
      "resource_type":"category"
    },
    {
      "id":313,
      "name":"Café",
      "parent":{
        "id":168,
        "resource_uri":"/v2/categories/168",
        "resource_type":"category"
      },
      "resource_uri":"/v2/categories/313",
      "resource_type":"category"
    },
    {
      "id":310,
      "name":"Sports d'hiver",
      "parent":{
        "id":170,
        "resource_uri":"/v2/categories/170",
        "resource_type":"category"
      },
      "resource_uri":"/v2/categories/310",
      "resource_type":"category"
    },
    {
      "id":309,
      "name":"Péage",
      "parent":{
        "id":165,
        "resource_uri":"/v2/categories/165",
        "resource_type":"category"
      },
      "resource_uri":"/v2/categories/309",
      "resource_type":"category"
    },
    {
      "id":308,
      "name":"Tabac",
      "parent":{
        "id":160,
        "resource_uri":"/v2/categories/160",
        "resource_type":"category"
      },
      "resource_uri":"/v2/categories/308",
      "resource_type":"category"
    },
    {
      "id":306,
      "name":"Services Bancaires",
      "parent":{
        "id":164,
        "resource_uri":"/v2/categories/164",
        "resource_type":"category"
      },
      "resource_uri":"/v2/categories/306",
      "resource_type":"category"
    },
    {
      "id":303,
      "name":"Retraits, Chq. et Vir.",
      "parent":null,
      "resource_uri":"/v2/categories/303",
      "resource_type":"category"
    },
    {
      "id":302,
      "name":"Taxes",
      "parent":{
        "id":159,
        "resource_uri":"/v2/categories/159",
        "resource_type":"category"
      },
      "resource_uri":"/v2/categories/302",
      "resource_type":"category"
    },
    {
      "id":294,
      "name":"Dons",
      "parent":{
        "id":160,
        "resource_uri":"/v2/categories/160",
        "resource_type":"category"
      },
      "resource_uri":"/v2/categories/294",
      "resource_type":"category"
    },
    {
      "id":293,
      "name":"Eau",
      "parent":{
        "id":161,
        "resource_uri":"/v2/categories/161",
        "resource_type":"category"
      },
      "resource_uri":"/v2/categories/293",
      "resource_type":"category"
    },
    {
      "id":289,
      "name":"Economies",
      "parent":{
        "id":2,
        "resource_uri":"/v2/categories/2",
        "resource_type":"category"
      },
      "resource_uri":"/v2/categories/289",
      "resource_type":"category"
    },
    {
      "id":288,
      "name":"Entretien véhicule",
      "parent":{
        "id":165,
        "resource_uri":"/v2/categories/165",
        "resource_type":"category"
      },
      "resource_uri":"/v2/categories/288",
      "resource_type":"category"
    },
    {
      "id":283,
      "name":"Remboursements",
      "parent":{
        "id":2,
        "resource_uri":"/v2/categories/2",
        "resource_type":"category"
      },
      "resource_uri":"/v2/categories/283",
      "resource_type":"category"
    },
    {
      "id":282,
      "name":"Virements internes",
      "parent":{
        "id":2,
        "resource_uri":"/v2/categories/2",
        "resource_type":"category"
      },
      "resource_uri":"/v2/categories/282",
      "resource_type":"category"
    },
    {
      "id":280,
      "name":"Abonnements - Autres",
      "parent":{
        "id":171,
        "resource_uri":"/v2/categories/171",
        "resource_type":"category"
      },
      "resource_uri":"/v2/categories/280",
      "resource_type":"category"
    },
    {
      "id":279,
      "name":"Retraite",
      "parent":{
        "id":2,
        "resource_uri":"/v2/categories/2",
        "resource_type":"category"
      },
      "resource_uri":"/v2/categories/279",
      "resource_type":"category"
    },
    {
      "id":278,
      "name":"Assurance",
      "parent":{
        "id":160,
        "resource_uri":"/v2/categories/160",
        "resource_type":"category"
      },
      "resource_uri":"/v2/categories/278",
      "resource_type":"category"
    },
    {
      "id":277,
      "name":"Téléphonie mobile",
      "parent":{
        "id":171,
        "resource_uri":"/v2/categories/171",
        "resource_type":"category"
      },
      "resource_uri":"/v2/categories/277",
      "resource_type":"category"
    },
    {
      "id":276,
      "name":"Autres dépenses",
      "parent":{
        "id":160,
        "resource_uri":"/v2/categories/160",
        "resource_type":"category"
      },
      "resource_uri":"/v2/categories/276",
      "resource_type":"category"
    },
    {
      "id":274,
      "name":"Fournitures de bureau",
      "parent":{
        "id":166,
        "resource_uri":"/v2/categories/166",
        "resource_type":"category"
      },
      "resource_uri":"/v2/categories/274",
      "resource_type":"category"
    },
    {
      "id":273,
      "name":"Supermarché / Epicerie",
      "parent":{
        "id":168,
        "resource_uri":"/v2/categories/168",
        "resource_type":"category"
      },
      "resource_uri":"/v2/categories/273",
      "resource_type":"category"
    },
    {
      "id":272,
      "name":"Vêtements/Chaussures",
      "parent":{
        "id":162,
        "resource_uri":"/v2/categories/162",
        "resource_type":"category"
      },
      "resource_uri":"/v2/categories/272",
      "resource_type":"category"
    },
    {
      "id":271,
      "name":"Dépôt d'argent",
      "parent":{
        "id":2,
        "resource_uri":"/v2/categories/2",
        "resource_type":"category"
      },
      "resource_uri":"/v2/categories/271",
      "resource_type":"category"
    },
    {
      "id":270,
      "name":"Services en ligne",
      "parent":{
        "id":166,
        "resource_uri":"/v2/categories/166",
        "resource_type":"category"
      },
      "resource_uri":"/v2/categories/270",
      "resource_type":"category"
    },
    {
      "id":269,
      "name":"Divertissements",
      "parent":{
        "id":170,
        "resource_uri":"/v2/categories/170",
        "resource_type":"category"
      },
      "resource_uri":"/v2/categories/269",
      "resource_type":"category"
    },
    {
      "id":268,
      "name":"Santé - Autres",
      "parent":{
        "id":163,
        "resource_uri":"/v2/categories/163",
        "resource_type":"category"
      },
      "resource_uri":"/v2/categories/268",
      "resource_type":"category"
    },
    {
      "id":267,
      "name":"Baby-sitters & Crèches",
      "parent":{
        "id":167,
        "resource_uri":"/v2/categories/167",
        "resource_type":"category"
      },
      "resource_uri":"/v2/categories/267",
      "resource_type":"category"
    },
    {
      "id":266,
      "name":"Jouets",
      "parent":{
        "id":167,
        "resource_uri":"/v2/categories/167",
        "resource_type":"category"
      },
      "resource_uri":"/v2/categories/266",
      "resource_type":"category"
    },
    {
      "id":265,
      "name":"Notes de frais",
      "parent":{
        "id":166,
        "resource_uri":"/v2/categories/166",
        "resource_type":"category"
      },
      "resource_uri":"/v2/categories/265",
      "resource_type":"category"
    },
    {
      "id":264,
      "name":"Location de véhicule",
      "parent":{
        "id":165,
        "resource_uri":"/v2/categories/165",
        "resource_type":"category"
      },
      "resource_uri":"/v2/categories/264",
      "resource_type":"category"
    },
    {
      "id":263,
      "name":"Hôtels",
      "parent":{
        "id":170,
        "resource_uri":"/v2/categories/170",
        "resource_type":"category"
      },
      "resource_uri":"/v2/categories/263",
      "resource_type":"category"
    },
    {
      "id":262,
      "name":"Articles de sport",
      "parent":{
        "id":162,
        "resource_uri":"/v2/categories/162",
        "resource_type":"category"
      },
      "resource_uri":"/v2/categories/262",
      "resource_type":"category"
    },
    {
      "id":261,
      "name":"Médecin",
      "parent":{
        "id":163,
        "resource_uri":"/v2/categories/163",
        "resource_type":"category"
      },
      "resource_uri":"/v2/categories/261",
      "resource_type":"category"
    },
    {
      "id":260,
      "name":"Fast foods",
      "parent":{
        "id":168,
        "resource_uri":"/v2/categories/168",
        "resource_type":"category"
      },
      "resource_uri":"/v2/categories/260",
      "resource_type":"category"
    },
    {
      "id":259,
      "name":"Prêt étudiant",
      "parent":{
        "id":167,
        "resource_uri":"/v2/categories/167",
        "resource_type":"category"
      },
      "resource_uri":"/v2/categories/259",
      "resource_type":"category"
    },
    {
      "id":258,
      "name":"Téléphonie fixe",
      "parent":{
        "id":171,
        "resource_uri":"/v2/categories/171",
        "resource_type":"category"
      },
      "resource_uri":"/v2/categories/258",
      "resource_type":"category"
    },
    {
      "id":251,
      "name":"Stationnement",
      "parent":{
        "id":165,
        "resource_uri":"/v2/categories/165",
        "resource_type":"category"
      },
      "resource_uri":"/v2/categories/251",
      "resource_type":"category"
    },
    {
      "id":249,
      "name":"Voyages / Vacances",
      "parent":{
        "id":170,
        "resource_uri":"/v2/categories/170",
        "resource_type":"category"
      },
      "resource_uri":"/v2/categories/249",
      "resource_type":"category"
    },
    {
      "id":248,
      "name":"Cosmétique",
      "parent":{
        "id":315,
        "resource_uri":"/v2/categories/315",
        "resource_type":"category"
      },
      "resource_uri":"/v2/categories/248",
      "resource_type":"category"
    },
    {
      "id":247,
      "name":"Assurance véhicule",
      "parent":{
        "id":165,
        "resource_uri":"/v2/categories/165",
        "resource_type":"category"
      },
      "resource_uri":"/v2/categories/247",
      "resource_type":"category"
    },
    {
      "id":246,
      "name":"Assurance habitation",
      "parent":{
        "id":161,
        "resource_uri":"/v2/categories/161",
        "resource_type":"category"
      },
      "resource_uri":"/v2/categories/246",
      "resource_type":"category"
    },
    {
      "id":245,
      "name":"Mutuelle",
      "parent":{
        "id":163,
        "resource_uri":"/v2/categories/163",
        "resource_type":"category"
      },
      "resource_uri":"/v2/categories/245",
      "resource_type":"category"
    },
    {
      "id":244,
      "name":"Sorties culturelles",
      "parent":{
        "id":170,
        "resource_uri":"/v2/categories/170",
        "resource_type":"category"
      },
      "resource_uri":"/v2/categories/244",
      "resource_type":"category"
    },
    {
      "id":243,
      "name":"Livres",
      "parent":{
        "id":162,
        "resource_uri":"/v2/categories/162",
        "resource_type":"category"
      },
      "resource_uri":"/v2/categories/243",
      "resource_type":"category"
    },
    {
      "id":242,
      "name":"Sport",
      "parent":{
        "id":170,
        "resource_uri":"/v2/categories/170",
        "resource_type":"category"
      },
      "resource_uri":"/v2/categories/242",
      "resource_type":"category"
    },
    {
      "id":241,
      "name":"Logement étudiant",
      "parent":{
        "id":167,
        "resource_uri":"/v2/categories/167",
        "resource_type":"category"
      },
      "resource_uri":"/v2/categories/241",
      "resource_type":"category"
    },
    {
      "id":240,
      "name":"Pensions",
      "parent":{
        "id":167,
        "resource_uri":"/v2/categories/167",
        "resource_type":"category"
      },
      "resource_uri":"/v2/categories/240",
      "resource_type":"category"
    },
    {
      "id":239,
      "name":"Ecole",
      "parent":{
        "id":167,
        "resource_uri":"/v2/categories/167",
        "resource_type":"category"
      },
      "resource_uri":"/v2/categories/239",
      "resource_type":"category"
    },
    {
      "id":238,
      "name":"Fournitures scolaires",
      "parent":{
        "id":167,
        "resource_uri":"/v2/categories/167",
        "resource_type":"category"
      },
      "resource_uri":"/v2/categories/238",
      "resource_type":"category"
    },
    {
      "id":237,
      "name":"Scolarité & Enfants - Autres",
      "parent":{
        "id":167,
        "resource_uri":"/v2/categories/167",
        "resource_type":"category"
      },
      "resource_uri":"/v2/categories/237",
      "resource_type":"category"
    },
    {
      "id":236,
      "name":"Pharmacie",
      "parent":{
        "id":163,
        "resource_uri":"/v2/categories/163",
        "resource_type":"category"
      },
      "resource_uri":"/v2/categories/236",
      "resource_type":"category"
    },
    {
      "id":235,
      "name":"Coiffeur",
      "parent":{
        "id":315,
        "resource_uri":"/v2/categories/315",
        "resource_type":"category"
      },
      "resource_uri":"/v2/categories/235",
      "resource_type":"category"
    },
    {
      "id":233,
      "name":"Extra",
      "parent":{
        "id":2,
        "resource_uri":"/v2/categories/2",
        "resource_type":"category"
      },
      "resource_uri":"/v2/categories/233",
      "resource_type":"category"
    },
    {
      "id":232,
      "name":"Services",
      "parent":{
        "id":2,
        "resource_uri":"/v2/categories/2",
        "resource_type":"category"
      },
      "resource_uri":"/v2/categories/232",
      "resource_type":"category"
    },
    {
      "id":231,
      "name":"Ventes",
      "parent":{
        "id":2,
        "resource_uri":"/v2/categories/2",
        "resource_type":"category"
      },
      "resource_uri":"/v2/categories/231",
      "resource_type":"category"
    },
    {
      "id":230,
      "name":"Salaires",
      "parent":{
        "id":2,
        "resource_uri":"/v2/categories/2",
        "resource_type":"category"
      },
      "resource_uri":"/v2/categories/230",
      "resource_type":"category"
    },
    {
      "id":227,
      "name":"Bars / Clubs",
      "parent":{
        "id":170,
        "resource_uri":"/v2/categories/170",
        "resource_type":"category"
      },
      "resource_uri":"/v2/categories/227",
      "resource_type":"category"
    },
    {
      "id":226,
      "name":"Hobbies",
      "parent":{
        "id":170,
        "resource_uri":"/v2/categories/170",
        "resource_type":"category"
      },
      "resource_uri":"/v2/categories/226",
      "resource_type":"category"
    },
    {
      "id":224,
      "name":"Frais Animaux",
      "parent":{
        "id":170,
        "resource_uri":"/v2/categories/170",
        "resource_type":"category"
      },
      "resource_uri":"/v2/categories/224",
      "resource_type":"category"
    },
    {
      "id":223,
      "name":"Loisirs & Sorties - Autres",
      "parent":{
        "id":170,
        "resource_uri":"/v2/categories/170",
        "resource_type":"category"
      },
      "resource_uri":"/v2/categories/223",
      "resource_type":"category"
    },
    {
      "id":222,
      "name":"Entretien",
      "parent":{
        "id":161,
        "resource_uri":"/v2/categories/161",
        "resource_type":"category"
      },
      "resource_uri":"/v2/categories/222",
      "resource_type":"category"
    },
    {
      "id":221,
      "name":"Décoration",
      "parent":{
        "id":161,
        "resource_uri":"/v2/categories/161",
        "resource_type":"category"
      },
      "resource_uri":"/v2/categories/221",
      "resource_type":"category"
    },
    {
      "id":220,
      "name":"Logement - Autres",
      "parent":{
        "id":161,
        "resource_uri":"/v2/categories/161",
        "resource_type":"category"
      },
      "resource_uri":"/v2/categories/220",
      "resource_type":"category"
    },
    {
      "id":219,
      "name":"Câble / Satellite",
      "parent":{
        "id":171,
        "resource_uri":"/v2/categories/171",
        "resource_type":"category"
      },
      "resource_uri":"/v2/categories/219",
      "resource_type":"category"
    },
    {
      "id":218,
      "name":"Gaz",
      "parent":{
        "id":161,
        "resource_uri":"/v2/categories/161",
        "resource_type":"category"
      },
      "resource_uri":"/v2/categories/218",
      "resource_type":"category"
    },
    {
      "id":217,
      "name":"Electricité",
      "parent":{
        "id":161,
        "resource_uri":"/v2/categories/161",
        "resource_type":"category"
      },
      "resource_uri":"/v2/categories/217",
      "resource_type":"category"
    },
    {
      "id":216,
      "name":"Loyer",
      "parent":{
        "id":161,
        "resource_uri":"/v2/categories/161",
        "resource_type":"category"
      },
      "resource_uri":"/v2/categories/216",
      "resource_type":"category"
    },
    {
      "id":209,
      "name":"Impôts fonciers",
      "parent":{
        "id":159,
        "resource_uri":"/v2/categories/159",
        "resource_type":"category"
      },
      "resource_uri":"/v2/categories/209",
      "resource_type":"category"
    },
    {
      "id":208,
      "name":"Impôts sur le revenu",
      "parent":{
        "id":159,
        "resource_uri":"/v2/categories/159",
        "resource_type":"category"
      },
      "resource_uri":"/v2/categories/208",
      "resource_type":"category"
    },
    {
      "id":207,
      "name":"Amendes",
      "parent":{
        "id":159,
        "resource_uri":"/v2/categories/159",
        "resource_type":"category"
      },
      "resource_uri":"/v2/categories/207",
      "resource_type":"category"
    },
    {
      "id":206,
      "name":"Impôts & Taxes - Autres",
      "parent":{
        "id":159,
        "resource_uri":"/v2/categories/159",
        "resource_type":"category"
      },
      "resource_uri":"/v2/categories/206",
      "resource_type":"category"
    },
    {
      "id":205,
      "name":"Frais d'impressions",
      "parent":{
        "id":166,
        "resource_uri":"/v2/categories/166",
        "resource_type":"category"
      },
      "resource_uri":"/v2/categories/205",
      "resource_type":"category"
    },
    {
      "id":204,
      "name":"Frais d'expéditions",
      "parent":{
        "id":166,
        "resource_uri":"/v2/categories/166",
        "resource_type":"category"
      },
      "resource_uri":"/v2/categories/204",
      "resource_type":"category"
    },
    {
      "id":203,
      "name":"Maintenance bureaux",
      "parent":{
        "id":166,
        "resource_uri":"/v2/categories/166",
        "resource_type":"category"
      },
      "resource_uri":"/v2/categories/203",
      "resource_type":"category"
    },
    {
      "id":202,
      "name":"Publicité",
      "parent":{
        "id":166,
        "resource_uri":"/v2/categories/166",
        "resource_type":"category"
      },
      "resource_uri":"/v2/categories/202",
      "resource_type":"category"
    },
    {
      "id":198,
      "name":"Billets d'avion",
      "parent":{
        "id":165,
        "resource_uri":"/v2/categories/165",
        "resource_type":"category"
      },
      "resource_uri":"/v2/categories/198",
      "resource_type":"category"
    },
    {
      "id":197,
      "name":"Billets de train",
      "parent":{
        "id":165,
        "resource_uri":"/v2/categories/165",
        "resource_type":"category"
      },
      "resource_uri":"/v2/categories/197",
      "resource_type":"category"
    },
    {
      "id":196,
      "name":"Transports en commun",
      "parent":{
        "id":165,
        "resource_uri":"/v2/categories/165",
        "resource_type":"category"
      },
      "resource_uri":"/v2/categories/196",
      "resource_type":"category"
    },
    {
      "id":195,
      "name":"Banque - Autres",
      "parent":{
        "id":164,
        "resource_uri":"/v2/categories/164",
        "resource_type":"category"
      },
      "resource_uri":"/v2/categories/195",
      "resource_type":"category"
    },
    {
      "id":194,
      "name":"Hypothèque",
      "parent":{
        "id":164,
        "resource_uri":"/v2/categories/164",
        "resource_type":"category"
      },
      "resource_uri":"/v2/categories/194",
      "resource_type":"category"
    },
    {
      "id":192,
      "name":"Epargne",
      "parent":{
        "id":164,
        "resource_uri":"/v2/categories/164",
        "resource_type":"category"
      },
      "resource_uri":"/v2/categories/192",
      "resource_type":"category"
    },
    {
      "id":191,
      "name":"Débit mensuel carte",
      "parent":{
        "id":164,
        "resource_uri":"/v2/categories/164",
        "resource_type":"category"
      },
      "resource_uri":"/v2/categories/191",
      "resource_type":"category"
    },
    {
      "id":188,
      "name":"Alimentation - Autres",
      "parent":{
        "id":168,
        "resource_uri":"/v2/categories/168",
        "resource_type":"category"
      },
      "resource_uri":"/v2/categories/188",
      "resource_type":"category"
    },
    {
      "id":186,
      "name":"Achats & Shopping - Autres",
      "parent":{
        "id":162,
        "resource_uri":"/v2/categories/162",
        "resource_type":"category"
      },
      "resource_uri":"/v2/categories/186",
      "resource_type":"category"
    },
    {
      "id":184,
      "name":"High Tech",
      "parent":{
        "id":162,
        "resource_uri":"/v2/categories/162",
        "resource_type":"category"
      },
      "resource_uri":"/v2/categories/184",
      "resource_type":"category"
    },
    {
      "id":183,
      "name":"Cadeaux",
      "parent":{
        "id":162,
        "resource_uri":"/v2/categories/162",
        "resource_type":"category"
      },
      "resource_uri":"/v2/categories/183",
      "resource_type":"category"
    },
    {
      "id":180,
      "name":"Internet",
      "parent":{
        "id":171,
        "resource_uri":"/v2/categories/171",
        "resource_type":"category"
      },
      "resource_uri":"/v2/categories/180",
      "resource_type":"category"
    },
    {
      "id":171,
      "name":"Abonnements",
      "parent":null,
      "resource_uri":"/v2/categories/171",
      "resource_type":"category"
    },
    {
      "id":170,
      "name":"Loisirs & Sorties",
      "parent":null,
      "resource_uri":"/v2/categories/170",
      "resource_type":"category"
    },
    {
      "id":168,
      "name":"Alimentation & Restau.",
      "parent":null,
      "resource_uri":"/v2/categories/168",
      "resource_type":"category"
    },
    {
      "id":167,
      "name":"Scolarité & Enfants",
      "parent":null,
      "resource_uri":"/v2/categories/167",
      "resource_type":"category"
    },
    {
      "id":166,
      "name":"Dépenses pro",
      "parent":null,
      "resource_uri":"/v2/categories/166",
      "resource_type":"category"
    },
    {
      "id":165,
      "name":"Auto & Transports",
      "parent":null,
      "resource_uri":"/v2/categories/165",
      "resource_type":"category"
    },
    {
      "id":164,
      "name":"Banque",
      "parent":null,
      "resource_uri":"/v2/categories/164",
      "resource_type":"category"
    },
    {
      "id":163,
      "name":"Santé",
      "parent":null,
      "resource_uri":"/v2/categories/163",
      "resource_type":"category"
    },
    {
      "id":162,
      "name":"Achats & Shopping",
      "parent":null,
      "resource_uri":"/v2/categories/162",
      "resource_type":"category"
    },
    {
      "id":161,
      "name":"Logement",
      "parent":null,
      "resource_uri":"/v2/categories/161",
      "resource_type":"category"
    },
    {
      "id":160,
      "name":"Divers",
      "parent":null,
      "resource_uri":"/v2/categories/160",
      "resource_type":"category"
    },
    {
      "id":159,
      "name":"Impôts & Taxes",
      "parent":null,
      "resource_uri":"/v2/categories/159",
      "resource_type":"category"
    },
    {
      "id":90,
      "name":"Dépenses pro - Autres",
      "parent":{
        "id":166,
        "resource_uri":"/v2/categories/166",
        "resource_type":"category"
      },
      "resource_uri":"/v2/categories/90",
      "resource_type":"category"
    },
    {
      "id":89,
      "name":"Remboursement emprunt",
      "parent":{
        "id":164,
        "resource_uri":"/v2/categories/164",
        "resource_type":"category"
      },
      "resource_uri":"/v2/categories/89",
      "resource_type":"category"
    },
    {
      "id":88,
      "name":"Chèques",
      "parent":{
        "id":303,
        "resource_uri":"/v2/categories/303",
        "resource_type":"category"
      },
      "resource_uri":"/v2/categories/88",
      "resource_type":"category"
    },
    {
      "id":87,
      "name":"Carburant",
      "parent":{
        "id":165,
        "resource_uri":"/v2/categories/165",
        "resource_type":"category"
      },
      "resource_uri":"/v2/categories/87",
      "resource_type":"category"
    },
    {
      "id":85,
      "name":"Retraits",
      "parent":{
        "id":303,
        "resource_uri":"/v2/categories/303",
        "resource_type":"category"
      },
      "resource_uri":"/v2/categories/85",
      "resource_type":"category"
    },
    {
      "id":84,
      "name":"Auto & Transports - Autres",
      "parent":{
        "id":165,
        "resource_uri":"/v2/categories/165",
        "resource_type":"category"
      },
      "resource_uri":"/v2/categories/84",
      "resource_type":"category"
    },
    {
      "id":83,
      "name":"Restaurants",
      "parent":{
        "id":168,
        "resource_uri":"/v2/categories/168",
        "resource_type":"category"
      },
      "resource_uri":"/v2/categories/83",
      "resource_type":"category"
    },
    {
      "id":80,
      "name":"Intérêts",
      "parent":{
        "id":2,
        "resource_uri":"/v2/categories/2",
        "resource_type":"category"
      },
      "resource_uri":"/v2/categories/80",
      "resource_type":"category"
    },
    {
      "id":79,
      "name":"Frais bancaires",
      "parent":{
        "id":164,
        "resource_uri":"/v2/categories/164",
        "resource_type":"category"
      },
      "resource_uri":"/v2/categories/79",
      "resource_type":"category"
    },
    {
      "id":78,
      "name":"Virements",
      "parent":{
        "id":303,
        "resource_uri":"/v2/categories/303",
        "resource_type":"category"
      },
      "resource_uri":"/v2/categories/78",
      "resource_type":"category"
    },
    {
      "id":3,
      "name":"Autres rentrées",
      "parent":{
        "id":2,
        "resource_uri":"/v2/categories/2",
        "resource_type":"category"
      },
      "resource_uri":"/v2/categories/3",
      "resource_type":"category"
    },
    {
      "id":2,
      "name":"Entrées d'argent",
      "parent":null,
      "resource_uri":"/v2/categories/2",
      "resource_type":"category"
    },
    {
      "id":1,
      "name":"A catégoriser",
      "parent":{
        "id":160,
        "resource_uri":"/v2/categories/160",
        "resource_type":"category"
      },
      "resource_uri":"/v2/categories/1",
      "resource_type":"category"
    }
  ],
  "pagination":{
    "previous_uri":null,
    "next_uri":null
  }
}
